normalizer_usps/__init__.py
normalizer_usps/normalizer.py
normalizer_usps/data/secondary_address_abbreviations.json
normalizer_usps/data/street_type_abbreviations.json
normalizer_usps-0.1.0.dist-info/LICENSE
normalizer_usps-0.1.0.dist-info/METADATA
normalizer_usps-0.1.0.dist-info/WHEEL
normalizer_usps-0.1.0.dist-info/top_level.txt
normalizer_usps-0.1.0.dist-info/RECORD
