Metadata-Version: 2.1
Name: normalizer-usps
Version: 0.1.0
Summary: A library for normalizing US addresses.
Home-page: https://github.com/larissabeatrizlima/normalizer_usps
Author: Larissa Lima
Author-email: larissabeatrizlima@outlook    .com
License: MIT
Classifier: Programming Language :: Python :: 3
Classifier: Operating System :: OS Independent
Requires-Python: >=3.6
License-File: LICENSE
Requires-Dist: pandas
Requires-Dist: importlib-resources ; python_version < "3.9"
